python_mommy/__init__.py
python_mommy/__main__.py
python_mommy-0.1.0.dist-info/LICENSE
python_mommy-0.1.0.dist-info/METADATA
python_mommy-0.1.0.dist-info/WHEEL
python_mommy-0.1.0.dist-info/top_level.txt
python_mommy-0.1.0.dist-info/RECORD
