Metadata-Version: 2.1
Name: python-mommy
Version: 0.1.0
Summary: Mommy's here to support you when running python~
Author-email: googer <googer@gmail.com>
Project-URL: Homepage, https://github.com/Def-Try/python-mommy
Project-URL: Bug Tracker, https://github.com/Def-Try/python-mommy/issues
Classifier: Programming Language :: Python :: 3
Classifier: License :: OSI Approved :: MIT License
Classifier: Operating System :: OS Independent
Requires-Python: >=3.8
License-File: LICENSE
